Metadata-Version: 2.1
Name: Aly-facts
Version: 1.0
Summary: A package that provides facts about an user on discord with the name of entity_night aka Aly aka Alyssa
Home-page: https://github.com/NotFaizen/Aly_facts
Author: NotFaizen
Author-email: munavir370@gmail.com
License: MIT
Keywords: aly,aly.py,aly_facts,facts
Platform: UNKNOWN
Classifier: Development Status :: 3 - Alpha
Classifier: Intended Audience :: Developers
Classifier: Topic :: Software Development :: Build Tools
Classifier: License :: OSI Approved :: MIT License
Classifier: Programming Language :: Python :: 3
Classifier: Programming Language :: Python :: 3.4
Classifier: Programming Language :: Python :: 3.5
Classifier: Programming Language :: Python :: 3.6
